miscutils/VERSION
miscutils/__init__.py
miscutils/dbg/__init__.py
miscutils/dbg/attrch.py
miscutils/func/__init__.py
miscutils/func/catch.py
miscutils/func/permisive.py
miscutils/func/retry.py
miscutils/insp/__init__.py
miscutils/insp/experimental/__init__.py
miscutils/insp/experimental/arginfo.py
miscutils/io/__init__.py
miscutils/io/experimental/__init__.py
miscutils/io/experimental/config.py
miscutils/io/prompt.py
miscutils/iter/__init__.py
miscutils/os/__init__.py
miscutils/os/experimental/__init__.py
miscutils/os/experimental/fs.py
miscutils/os/experimental/shell.py
miscutils/str/__init__.py
miscutils/tools/__init__.py
miscutils/tools/experimental/__init__.py
miscutils/tools/experimental/listing.py
miscutils/tools/experimental/listing_here.py
miscutils/tools/experimental/magic_with.py
miscutils/user/__init__.py
miscutils/user/box.py
miscutils/user/experimental/__init__.py
miscutils/user/experimental/attrext.py
miscutils/user/proxy.py
miscutils/user/routers.py
miscutils/user/tree.py
miscutils-1.4.0.dist-info/entry_points.txt
miscutils-1.4.0.dist-info/WHEEL
miscutils-1.4.0.dist-info/METADATA
miscutils-1.4.0.dist-info/RECORD
