Metadata-Version: 2.1
Name: miscutils
Version: 1.4.0
Summary: Miscellaneous utilities for general use
License: MIT
Keywords: iterating,head,tail,listing,router,proxy,prompt,shell
Author: Grzegorz Krason
Author-email: grzegorz.krason@gmail.com
Requires-Python: >=3.6,<4.0
Classifier: License :: OSI Approved :: MIT License
Classifier: Programming Language :: Python :: 3
Classifier: Programming Language :: Python :: 3.6
Classifier: Programming Language :: Python :: 3.7
Classifier: Programming Language :: Python :: 3.8
Requires-Dist: ruamel.yaml (>=0.16.7,<0.17.0)
